adafruit_lcd_plate_menu
