Metadata-Version: 1.1
Name: adafruit-lcd-plate-menu
Version: 2.0.1
Summary: A simple yet powerful menu library for Adafruit's LCD plates
Home-page: https://www.github.com/rodrigodiez/adafruit_lcd_plate_menu
Author: Rodrigo Diez Villamuera
Author-email: rodrigo@rodrigodiez.io
License: UNKNOWN
Download-URL: https://github.com/rodrigodiez/adafruit_lcd_plate_menu/archive/2.0.1.tar.gz
Platform: UNKNOWN
Classifier: Development Status :: 3 - Alpha
Classifier: Environment :: Console
Classifier: Intended Audience :: Developers
Classifier: License :: OSI Approved :: MIT License
Classifier: Natural Language :: English
Classifier: Operating System :: OS Independent
Classifier: Programming Language :: Python :: 2.7
Classifier: Topic :: Software Development
